{
    "dados do circuito": [
        {
            "name": "Tipo",
            "type": "Serie"
        },
        {
            "name": "Vtotal (Vcc)",
            "value": 5000
        },
        {
            "name": "Rtotal",
            "value": 2000
        },
        {
            "name": "Itotal",
            "value": 2.5
        }
    ],
    "resistores": [
        {
            "name": "R1",
            "value": 1000,
            "tolerance": 5,
            "tensao": 2500.0
        },
        {
            "name": "R2",
            "value": 1000,
            "tolerance": 5,
            "tensao": 2500.0
        }
    ]
}